{
   "type":"FeatureCollection",
   "features":[
      {
         "type":"Feature",
         "properties":{
            "ID":1,
            "Aire":328.499791,
            "Hauteur":11.986445,
            "Type":"Roof"
         },
         "geometry":{
            "type":"Polygon",
            "coordinates":[
               [
                  [
                     1051213.677483,
                     6840591.307232,
                     150.986445
                  ],
                  [
                     1051207.06699,
                     6840573.935737,
                     150.986445
                  ],
                  [
                     1051198.533028,
                     6840577.164949,
                     150.986445
                  ],
                  [
                     1051205.008084,
                     6840594.563849,
                     150.986445
                  ],
                  [
                     1051210.858899,
                     6840610.428091,
                     150.986445
                  ],
                  [
                     1051219.655959,
                     6840607.123519,
                     150.986445
                  ],
                  [
                     1051213.677483,
                     6840591.307232,
                     150.986445
                  ]
               ]
            ]
         }
      },
      {
         "type":"Feature",
         "properties":{
            "ID":19,
            "Aire":145.143492,
            "Hauteur":11.85698,
            "Type":"Roof"
         },
         "geometry":{
            "type":"MultiPolygon",
            "coordinates":[
               [
                  [
                     [
                        1051202.695276,
                        6840614.849142,
                        147.017341
                     ],
                     [
                        1051204.053789,
                        6840614.12689,
                        147.017341
                     ],
                     [
                        1051197.704933,
                        6840597.691531,
                        147.017341
                     ],
                     [
                        1051190.080067,
                        6840600.63696,
                        147.017341
                     ],
                     [
                        1051196.428923,
                        6840617.072319,
                        147.017341
                     ],
                     [
                        1051197.862701,
                        6840616.682737,
                        147.017341
                     ],
                     [
                        1051191.726643,
                        6840600.213922,
                        147.017341
                     ],
                     [
                        1051196.570029,
                        6840598.409342,
                        147.017341
                     ],
                     [
                        1051202.695276,
                        6840614.849142,
                        147.017341
                     ]
                  ]
               ],
               [
                  [
                     [
                        1051197.862701,
                        6840616.682737,
                        150.85698
                     ],
                     [
                        1051202.695276,
                        6840614.849142,
                        150.85698
                     ],
                     [
                        1051196.570029,
                        6840598.409342,
                        150.85698
                     ],
                     [
                        1051191.726643,
                        6840600.213922,
                        150.85698
                     ],
                     [
                        1051197.862701,
                        6840616.682737,
                        150.85698
                     ]
                  ]
               ]
            ]
         }
      },
      {
         "type":"Feature",
         "properties":{
            "ID":3,
            "Aire":160.799356,
            "Hauteur":11.975563,
            "Type":"Roof"
         },
         "geometry":{
            "type":"MultiPolygon",
            "coordinates":[
               [
                  [
                     [
                        1051164.063278,
                        6840612.692497,
                        147.153628
                     ],
                     [
                        1051162.676975,
                        6840613.305024,
                        147.153628
                     ],
                     [
                        1051169.144747,
                        6840629.955404,
                        147.153628
                     ],
                     [
                        1051170.629174,
                        6840629.451813,
                        147.153628
                     ],
                     [
                        1051164.063278,
                        6840612.692497,
                        147.153628
                     ]
                  ]
               ],
               [
                  [
                     [
                        1051170.629174,
                        6840629.451813,
                        150.975563
                     ],
                     [
                        1051176.08296,
                        6840627.324237,
                        150.975563
                     ],
                     [
                        1051169.517064,
                        6840610.564921,
                        150.975563
                     ],
                     [
                        1051164.063278,
                        6840612.692497,
                        150.975563
                     ],
                     [
                        1051170.629174,
                        6840629.451813,
                        150.975563
                     ]
                  ]
               ],
               [
                  [
                     [
                        1051176.08296,
                        6840627.324237,
                        147.153628
                     ],
                     [
                        1051177.483047,
                        6840626.716426,
                        147.153628
                     ],
                     [
                        1051171.015275,
                        6840610.066046,
                        147.153628
                     ],
                     [
                        1051169.517064,
                        6840610.564921,
                        147.153628
                     ],
                     [
                        1051176.08296,
                        6840627.324237,
                        147.153628
                     ]
                  ]
               ]
            ]
         }
      },
      {
         "type":"Feature",
         "properties":{
            "ID":5,
            "Aire":174.970776,
            "Hauteur":11.987181,
            "Type":"Roof"
         },
         "geometry":{
            "type":"MultiPolygon",
            "coordinates":[
               [
                  [
                     [
                        1051189.842944,
                        6840620.928328,
                        147.258277
                     ],
                     [
                        1051191.197609,
                        6840620.333093,
                        147.258277
                     ],
                     [
                        1051184.765155,
                        6840603.643913,
                        147.258277
                     ],
                     [
                        1051183.336965,
                        6840604.143864,
                        147.258277
                     ],
                     [
                        1051189.842944,
                        6840620.928328,
                        147.258277
                     ]
                  ]
               ],
               [
                  [
                     [
                        1051183.336965,
                        6840604.143864,
                        150.987181
                     ],
                     [
                        1051177.765903,
                        6840606.297205,
                        150.987181
                     ],
                     [
                        1051184.271881,
                        6840623.081669,
                        150.987181
                     ],
                     [
                        1051189.842944,
                        6840620.928328,
                        150.987181
                     ],
                     [
                        1051183.336965,
                        6840604.143864,
                        150.987181
                     ]
                  ]
               ],
               [
                  [
                     [
                        1051178.952977,
                        6840613.558732,
                        144.496066
                     ],
                     [
                        1051177.912377,
                        6840613.947415,
                        144.496066
                     ],
                     [
                        1051181.84839,
                        6840624.485087,
                        144.496066
                     ],
                     [
                        1051183.437105,
                        6840623.891673,
                        144.496066
                     ],
                     [
                        1051183.030911,
                        6840623.480756,
                        144.496066
                     ],
                     [
                        1051178.952977,
                        6840613.558732,
                        144.496066
                     ]
                  ]
               ],
               [
                  [
                     [
                        1051183.030911,
                        6840623.480756,
                        147.258277
                     ],
                     [
                        1051184.271881,
                        6840623.081669,
                        147.258277
                     ],
                     [
                        1051177.765903,
                        6840606.297205,
                        147.258277
                     ],
                     [
                        1051176.377551,
                        6840606.876719,
                        147.258277
                     ],
                     [
                        1051178.952977,
                        6840613.558732,
                        147.258277
                     ],
                     [
                        1051183.030911,
                        6840623.480756,
                        147.258277
                     ]
                  ]
               ]
            ]
         }
      },
      {
         "type":"Feature",
         "properties":{
            "ID":7,
            "Aire":365.418494,
            "Hauteur":11.985775,
            "Type":"Roof"
         },
         "geometry":{
            "type":"MultiPolygon",
            "coordinates":[
               [
                  [
                     [
                        1051150.163567,
                        6840619.304333,
                        146.771963
                     ],
                     [
                        1051147.515144,
                        6840620.439984,
                        146.771963
                     ],
                     [
                        1051154.645748,
                        6840637.069085,
                        146.771963
                     ],
                     [
                        1051164.111106,
                        6840633.010314,
                        146.771963
                     ],
                     [
                        1051156.980502,
                        6840616.381213,
                        146.771963
                     ],
                     [
                        1051156.038606,
                        6840616.650564,
                        146.771963
                     ],
                     [
                        1051162.624785,
                        6840633.514983,
                        146.771963
                     ],
                     [
                        1051161.103888,
                        6840634.104943,
                        146.771963
                     ],
                     [
                        1051156.589215,
                        6840635.85389,
                        146.771963
                     ],
                     [
                        1051150.163567,
                        6840619.304333,
                        146.771963
                     ]
                  ]
               ],
               [
                  [
                     [
                        1051156.038606,
                        6840616.650564,
                        150.695338
                     ],
                     [
                        1051154.565596,
                        6840617.307954,
                        150.695338
                     ],
                     [
                        1051161.103888,
                        6840634.104943,
                        150.695338
                     ],
                     [
                        1051162.624785,
                        6840633.514983,
                        150.695338
                     ],
                     [
                        1051156.038606,
                        6840616.650564,
                        150.695338
                     ]
                  ]
               ],
               [
                  [
                     [
                        1051161.103888,
                        6840634.104943,
                        150.985775
                     ],
                     [
                        1051154.565596,
                        6840617.307954,
                        150.985775
                     ],
                     [
                        1051150.190489,
                        6840606.256752,
                        150.985775
                     ],
                     [
                        1051148.128872,
                        6840600.738736,
                        150.985775
                     ],
                     [
                        1051129.800415,
                        6840607.335746,
                        150.985775
                     ],
                     [
                        1051131.76921,
                        6840612.805644,
                        150.985775
                     ],
                     [
                        1051141.94546,
                        6840609.142879,
                        150.985775
                     ],
                     [
                        1051146.811768,
                        6840610.869851,
                        150.985775
                     ],
                     [
                        1051150.163567,
                        6840619.304333,
                        150.985775
                     ],
                     [
                        1051156.589215,
                        6840635.85389,
                        150.985775
                     ],
                     [
                        1051161.103888,
                        6840634.104943,
                        150.985775
                     ]
                  ]
               ]
            ]
         }
      },
      {
         "type":"Feature",
         "properties":{
            "ID":9,
            "Aire":104.361527,
            "Hauteur":8.53059,
            "Type":"Roof"
         },
         "geometry":{
            "type":"MultiPolygon",
            "coordinates":[
               [
                  [
                     [
                        1051136.555658,
                        6840645.647871,
                        144.485747
                     ],
                     [
                        1051137.625844,
                        6840645.160121,
                        144.485747
                     ],
                     [
                        1051132.984192,
                        6840634.892006,
                        144.485747
                     ],
                     [
                        1051131.912204,
                        6840635.376593,
                        144.485747
                     ],
                     [
                        1051136.555658,
                        6840645.647871,
                        144.485747
                     ]
                  ]
               ],
               [
                  [
                     [
                        1051131.912204,
                        6840635.376593,
                        147.53059
                     ],
                     [
                        1051128.955073,
                        6840628.835447,
                        147.53059
                     ],
                     [
                        1051125.137137,
                        6840630.561465,
                        147.53059
                     ],
                     [
                        1051128.094216,
                        6840637.102497,
                        147.53059
                     ],
                     [
                        1051132.737696,
                        6840647.373831,
                        147.53059
                     ],
                     [
                        1051136.555658,
                        6840645.647871,
                        147.53059
                     ],
                     [
                        1051131.912204,
                        6840635.376593,
                        147.53059
                     ]
                  ]
               ],
               [
                  [
                     [
                        1051128.094216,
                        6840637.102497,
                        144.485747
                     ],
                     [
                        1051126.978836,
                        6840637.606699,
                        144.485747
                     ],
                     [
                        1051131.620488,
                        6840647.874814,
                        144.485747
                     ],
                     [
                        1051132.737696,
                        6840647.373831,
                        144.485747
                     ],
                     [
                        1051128.094216,
                        6840637.102497,
                        144.485747
                     ]
                  ]
               ]
            ]
         }
      },
      {
         "type":"Feature",
         "properties":{
            "ID":11,
            "Aire":147.202423,
            "Hauteur":11.994598,
            "Type":"Roof"
         },
         "geometry":{
            "type":"MultiPolygon",
            "coordinates":[
               [
                  [
                     [
                        1051148.102253,
                        6840640.346126,
                        147.255856
                     ],
                     [
                        1051149.431521,
                        6840639.707138,
                        147.255856
                     ],
                     [
                        1051141.935003,
                        6840622.965474,
                        147.255856
                     ],
                     [
                        1051140.560853,
                        6840623.577046,
                        147.255856
                     ],
                     [
                        1051148.102253,
                        6840640.346126,
                        147.255856
                     ]
                  ]
               ],
               [
                  [
                     [
                        1051140.560853,
                        6840623.577046,
                        150.994598
                     ],
                     [
                        1051136.711946,
                        6840625.304234,
                        150.994598
                     ],
                     [
                        1051135.941619,
                        6840625.650666,
                        150.994598
                     ],
                     [
                        1051143.482739,
                        6840642.419124,
                        150.994598
                     ],
                     [
                        1051148.102253,
                        6840640.346126,
                        150.994598
                     ],
                     [
                        1051140.560853,
                        6840623.577046,
                        150.994598
                     ]
                  ]
               ],
               [
                  [
                     [
                        1051134.624993,
                        6840626.238722,
                        147.255856
                     ],
                     [
                        1051142.121511,
                        6840642.980386,
                        147.255856
                     ],
                     [
                        1051143.482739,
                        6840642.419124,
                        147.255856
                     ],
                     [
                        1051135.941619,
                        6840625.650666,
                        147.255856
                     ],
                     [
                        1051134.624993,
                        6840626.238722,
                        147.255856
                     ]
                  ]
               ]
            ]
         }
      },
      {
         "type":"Feature",
         "properties":{
            "ID":13,
            "Aire":142.924987,
            "Hauteur":10.620988,
            "Type":"Roof"
         },
         "geometry":{
            "type":"MultiPolygon",
            "coordinates":[
               [
                  [
                     [
                        1051116.658729,
                        6840642.279626,
                        144.669222
                     ],
                     [
                        1051114.850618,
                        6840643.099233,
                        144.669222
                     ],
                     [
                        1051119.520892,
                        6840653.402189,
                        144.669222
                     ],
                     [
                        1051121.229953,
                        6840652.637555,
                        144.669222
                     ],
                     [
                        1051116.658729,
                        6840642.279626,
                        144.669222
                     ]
                  ]
               ],
               [
                  [
                     [
                        1051121.229953,
                        6840652.637555,
                        149.620988
                     ],
                     [
                        1051126.16797,
                        6840650.428794,
                        149.620988
                     ],
                     [
                        1051121.585854,
                        6840640.046187,
                        149.620988
                     ],
                     [
                        1051118.765654,
                        6840633.6559,
                        149.620988
                     ],
                     [
                        1051113.816746,
                        6840635.839982,
                        149.620988
                     ],
                     [
                        1051116.658729,
                        6840642.279626,
                        149.620988
                     ],
                     [
                        1051121.229953,
                        6840652.637555,
                        149.620988
                     ]
                  ]
               ],
               [
                  [
                     [
                        1051126.16797,
                        6840650.428794,
                        144.669222
                     ],
                     [
                        1051127.961134,
                        6840649.576273,
                        144.669222
                     ],
                     [
                        1051123.29086,
                        6840639.273317,
                        144.669222
                     ],
                     [
                        1051121.585854,
                        6840640.046187,
                        144.669222
                     ],
                     [
                        1051126.16797,
                        6840650.428794,
                        144.669222
                     ]
                  ]
               ]
            ]
         }
      },
      {
         "type":"Feature",
         "properties":{
            "ID":15,
            "Aire":156.153095,
            "Hauteur":11.919697,
            "Type":"Roof"
         },
         "geometry":{
            "type":"MultiPolygon",
            "coordinates":[
               [
                  [
                     [
                        1051101.604028,
                        6840641.343985,
                        147.119949
                     ],
                     [
                        1051100.285932,
                        6840641.93186,
                        147.119949
                     ],
                     [
                        1051107.729873,
                        6840658.767013,
                        147.119949
                     ],
                     [
                        1051109.113174,
                        6840658.173163,
                        147.119949
                     ],
                     [
                        1051101.604028,
                        6840641.343985,
                        147.119949
                     ]
                  ]
               ],
               [
                  [
                     [
                        1051109.113174,
                        6840658.173163,
                        150.919697
                     ],
                     [
                        1051113.487479,
                        6840656.230181,
                        150.919697
                     ],
                     [
                        1051105.978334,
                        6840639.401003,
                        150.919697
                     ],
                     [
                        1051101.604028,
                        6840641.343985,
                        150.919697
                     ],
                     [
                        1051109.113174,
                        6840658.173163,
                        150.919697
                     ]
                  ]
               ],
               [
                  [
                     [
                        1051114.854107,
                        6840655.558349,
                        144.465382
                     ],
                     [
                        1051115.793269,
                        6840655.090601,
                        144.465382
                     ],
                     [
                        1051111.268204,
                        6840644.708077,
                        144.465382
                     ],
                     [
                        1051110.252263,
                        6840645.15086,
                        144.465382
                     ],
                     [
                        1051114.854107,
                        6840655.558349,
                        144.465382
                     ]
                  ]
               ],
               [
                  [
                     [
                        1051110.252263,
                        6840645.15086,
                        147.119949
                     ],
                     [
                        1051107.431827,
                        6840638.772185,
                        147.119949
                     ],
                     [
                        1051105.978334,
                        6840639.401003,
                        147.119949
                     ],
                     [
                        1051113.487479,
                        6840656.230181,
                        147.119949
                     ],
                     [
                        1051114.854107,
                        6840655.558349,
                        147.119949
                     ],
                     [
                        1051110.252263,
                        6840645.15086,
                        147.119949
                     ]
                  ]
               ]
            ]
         }
      },
      {
         "type":"Feature",
         "properties":{
            "ID":17,
            "Aire":206.258219,
            "Hauteur":11.999785,
            "Type":"Roof"
         },
         "geometry":{
            "type":"MultiPolygon",
            "coordinates":[
               [
                  [
                     [
                        1051099.741926,
                        6840659.389297,
                        149.026598
                     ],
                     [
                        1051100.420407,
                        6840659.088163,
                        149.026598
                     ],
                     [
                        1051093.500385,
                        6840643.496727,
                        149.026598
                     ],
                     [
                        1051085.131165,
                        6840647.211279,
                        149.026598
                     ],
                     [
                        1051085.497348,
                        6840648.036322,
                        149.026598
                     ],
                     [
                        1051092.68577,
                        6840644.605386,
                        149.026598
                     ],
                     [
                        1051099.741926,
                        6840659.389297,
                        149.026598
                     ]
                  ]
               ],
               [
                  [
                     [
                        1051085.497348,
                        6840648.036322,
                        150.999785
                     ],
                     [
                        1051083.97798,
                        6840648.761495,
                        150.999785
                     ],
                     [
                        1051092.159682,
                        6840665.903626,
                        150.999785
                     ],
                     [
                        1051100.867472,
                        6840661.747517,
                        150.999785
                     ],
                     [
                        1051099.741926,
                        6840659.389297,
                        150.999785
                     ],
                     [
                        1051092.68577,
                        6840644.605386,
                        150.999785
                     ],
                     [
                        1051085.497348,
                        6840648.036322,
                        150.999785
                     ]
                  ]
               ]
            ]
         }
      }
   ]
}